mssw/__init__.py
mssw/bindings/_cpp.cpp
mssw/bindings/_cpp.modules
mssw/bindings/_cpp.sources
mssw/bindings/ssw_cpp20.cpp
mssw/cpp/__init__.py
mssw/cpp/__init__.pyi
mssw/py.typed
mssw/src/kseq.h
mssw/src/main.c
mssw/src/sse2neon.h
mssw/src/ssw.c
mssw/src/ssw.h
mssw/src/ssw_cpp20.cpp
mssw/src/ssw_cpp20.hpp
mssw/_cpp.cpython-310-x86_64-linux-gnu.so
mssw-0.1.5.dist-info/WHEEL
mssw-0.1.5.dist-info/METADATA
mssw-0.1.5.dist-info/RECORD
