Metadata-Version: 2.1
Name: mssw
Version: 0.1.5
Summary: Modern Cpp binding for complete-striped-smith-watern-library
License: MIT
Keywords: smith-watern,alignment,bioinformatics
Author: Yangyang Li
Author-email: yangyang.li@northwestern.edu
Requires-Python: >=3.7,<4.0
Classifier: Development Status :: 4 - Beta
Classifier: Environment :: Console
Classifier: Intended Audience :: Developers
Classifier: Intended Audience :: End Users/Desktop
Classifier: Intended Audience :: System Administrators
Classifier: License :: OSI Approved :: MIT License
Classifier: Operating System :: MacOS
Classifier: Operating System :: Unix
Classifier: Programming Language :: Python
Classifier: Programming Language :: Python :: 3
Classifier: Programming Language :: Python :: 3.7
Classifier: Programming Language :: Python :: 3.8
Classifier: Programming Language :: Python :: 3.9
Classifier: Programming Language :: Python :: 3.10
Requires-Dist: pybind11 (>=2.10.0,<3.0.0)
Requires-Dist: rich (>=12.6.0,<13.0.0)
Requires-Dist: setuptools (>=65.4.1,<66.0.0)
